<?xml version="1.0" encoding="UTF-8"?>
<LanguageData>

  <Hungry.stages.0.label>หิว</Hungry.stages.0.label>
  <Hungry.stages.0.description>ฉันไม่ได้กินอะไรมากสักพักแล้ว</Hungry.stages.0.description>
  <Hungry.stages.1.label>หิวมาก</Hungry.stages.1.label>
  <Hungry.stages.1.description>ความหิวเสียดแทงอยู่ข้างใน ฉันต้องการอาหารหรือไม่อย่างนั้นฉันจะอดตายในอีกไม่นาน</Hungry.stages.1.description>
  <Hungry.stages.2.label>อดอยาก</Hungry.stages.2.label>
  <Hungry.stages.2.description>ฉันแค่ต้องการบางอย่าง - อะไรก็ได้ - เพื่อกิน ฉันรู้สึกได้ว่าร่างกายกำลังเสียไป มันเจ็บ</Hungry.stages.2.description>

  <Tired.stages.0.label>เหนื่อย</Tired.stages.0.label>
  <Tired.stages.0.description>ฉันไม่ได้นอนมาสักพักแล้ว</Tired.stages.0.description>
  <Tired.stages.1.label>เหนื่อยมาก</Tired.stages.1.label>
  <Tired.stages.1.description>ฉันเหนื่อยเหลือเกิน ฉันแค่ต้องการนอนลงและพักผ่อนสักไม่กี่นาที...</Tired.stages.1.description>
  <Tired.stages.2.label>หมดแรง</Tired.stages.2.label>
  <Tired.stages.2.description>ฉันหมดแรงเหลือเกินจนแทบจะยืนไม่ไหวแล้ว หนังตาของฉันช่างหนัก ให้ฉันนอนเถอะ...</Tired.stages.2.description>

  <JoyLevel.stages.0.label>ถูกลิดรอนความสุขอย่างสิ้นเชิง</JoyLevel.stages.0.label>
  <JoyLevel.stages.0.description>มันนานมากแล้วตั้งแต่ที่ฉันได้ทำอะไรที่มีความสุขจริงๆ</JoyLevel.stages.0.description>
  <JoyLevel.stages.1.label>ถูกลิดรอนความสุขอย่างมาก</JoyLevel.stages.1.label>
  <JoyLevel.stages.1.description>ฉันไม่เคยได้พักผ่อนและมีความสุขรอบๆที่นี่เลย</JoyLevel.stages.1.description>
  <JoyLevel.stages.2.label>ถูกลิดรอนความสุข</JoyLevel.stages.2.label>
  <JoyLevel.stages.2.description>ฉันอยากพักเพื่อหาความสุขบ้าง</JoyLevel.stages.2.description>
  <JoyLevel.stages.3.label>ความสุขเติมเต็ม</JoyLevel.stages.3.label>
  <JoyLevel.stages.3.description>ฉันมีเวลาที่เยี่ยมที่นี่เมื่อไม่นานนี้</JoyLevel.stages.3.description>
  <JoyLevel.stages.4.label>สุขแสนสุข</JoyLevel.stages.4.label>
  <JoyLevel.stages.4.description>ฉันมีความสุขมากเหลือเกิน ฉันรักที่นี่!</JoyLevel.stages.4.description>

  <ComfortLevel.stages.0.label>ไม่สะดวกสบาย</ComfortLevel.stages.0.label>
  <ComfortLevel.stages.0.description>เดี๋ยวนี้ฉันไม่ค่อยสะดวกสบาย เราต้องหาอะไรนุ่มๆสักอย่างมานั่งแถวๆนี้บ้างแล้ว</ComfortLevel.stages.0.description>
  <ComfortLevel.stages.1.label>สะดวกสบาย</ComfortLevel.stages.1.label>
  <ComfortLevel.stages.1.description>เดี๋ยวนี้ฉันสะดวกสบายดี</ComfortLevel.stages.1.description>
  <ComfortLevel.stages.2.label>สะดสกสบายมาก</ComfortLevel.stages.2.label>
  <ComfortLevel.stages.2.description>เดี๋ยวนี้ฉันสะดวกสบายมาก</ComfortLevel.stages.2.description>
  <ComfortLevel.stages.3.label>สะดวกสบายสุดๆ</ComfortLevel.stages.3.label>
  <ComfortLevel.stages.3.description>เดี๋ยวนี้ฉันสะดวกสบายสุดๆเลย !</ComfortLevel.stages.3.description>
  <ComfortLevel.stages.4.label>สะดวกสบายหรูหราโอ่อ่า</ComfortLevel.stages.4.label>
  <ComfortLevel.stages.4.description>ฉันกำลังพักอยู่บนเมฆในสรวงสวรรค์สินะ</ComfortLevel.stages.4.description>

  <EnvironmentUgly.stages.0.label>บรรยากาศน่าเกลียด</EnvironmentUgly.stages.0.label>
  <EnvironmentUgly.stages.0.description>ที่นี่ไม่น่าอยู่เลย</EnvironmentUgly.stages.0.description>
  <EnvironmentUgly.stages.1.label>บรรยากาศอุบาทว์</EnvironmentUgly.stages.1.label>
  <EnvironmentUgly.stages.1.description>ที่นี่ไม่น่าอยู่อย่างมาก ฉันไม่อยากอยู่ที่นี่</EnvironmentUgly.stages.1.description>
  <EnvironmentUgly.stages.2.label>บรรยากาศมืดมน</EnvironmentUgly.stages.2.label>
  <EnvironmentUgly.stages.2.description>ที่นี่ไม่อาจจะทานทนได้ ปล่อยฉันออกไปนะ...</EnvironmentUgly.stages.2.description>
  <EnvironmentPretty.stages.0.label>บรรยากาศรื่นรม</EnvironmentPretty.stages.0.label>
  <EnvironmentPretty.stages.0.description>ที่นี่น่าอยู่ดี</EnvironmentPretty.stages.0.description>
  <EnvironmentPretty.stages.1.label>บรรยากาศรื่นรมมาก</EnvironmentPretty.stages.1.label>
  <EnvironmentPretty.stages.1.description>ฉันชอบที่นี่ มันสวยดี</EnvironmentPretty.stages.1.description>
  <EnvironmentPretty.stages.2.label>บรรยากาศสวยสดงดงาม</EnvironmentPretty.stages.2.label>
  <EnvironmentPretty.stages.2.description>ที่นี่สวยสดงดงามมาก มันทำให้ฉันร่าเริงและทำให้รักชีวิตของฉัน</EnvironmentPretty.stages.2.description>

  <EnvironmentCramped.stages.0.label>บรรยากาศคับแคบ</EnvironmentCramped.stages.0.label>
  <EnvironmentCramped.stages.0.description>ที่นี่คับแคบมาก ฉันรู้สึกว่าไม่มีที่จะหายใจ</EnvironmentCramped.stages.0.description>
  <EnvironmentCramped.stages.1.label>บรรยากาศคับแคบมาก</EnvironmentCramped.stages.1.label>
  <EnvironmentCramped.stages.1.description>มันอึดอัดมากในนี้ ฉันไม่มีที่จะขยับตัวเลย ฉันรู้สึกเหมือนหนูที่อยู่ในกรงแคบๆ</EnvironmentCramped.stages.1.description>

  <EnvironmentSpaciousInterior.stages.0.label>ภายในกว้างขวาง</EnvironmentSpaciousInterior.stages.0.label>
  <EnvironmentSpaciousInterior.stages.0.description>ที่นี่เป็นพื้นที่เปิดในร่มที่สบายมากๆ</EnvironmentSpaciousInterior.stages.0.description>

</LanguageData>
