<?xml version="1.0" encoding="UTF-8"?>
<LanguageData>
  
  <!-- EN: farmer -->
  <Farmer.label>ชาวนา</Farmer.label>
  
  <!-- EN: hunter -->
  <Hunter.label>นักล่า</Hunter.label>
  
  <!-- EN: logger -->
  <Logger.label>คนตัดไม้</Logger.label>
  
  <!-- EN: miner -->
  <Miner.label>คนขุดแร่</Miner.label>
  
  <!-- EN: farmer -->
  <Tribal_Farmer.label>ชาวนา</Tribal_Farmer.label>
  
  <!-- EN: logger -->
  <Tribal_Logger.label>คนตัดไม้</Tribal_Logger.label>
  
  <!-- EN: miner -->
  <Tribal_Miner.label>คนขุดแร่</Tribal_Miner.label>
  
</LanguageData>