<?xml version="1.0" encoding="UTF-8"?>
<LanguageData>

	<GlobalUtility.rulePack.rulesStrings>
		<li>quantity_adjphrase->กลุ่ม</li>
		<li>quantity_adjphrase->บางส่วน</li>
		<li>quantity_adjphrase->หลายสิบ</li>
		<li>quantity_adjphrase->สอง</li>
		<li>quantity_adjphrase->สาม</li>
		<li>quantity_adjphrase->สี่</li>
		<li>quantity_adjphrase->ห้า</li>
		<li>quantity_adjphrase->หก</li>
		<li>quantity_adjphrase->อนันต์</li>
		<li>quantity_adjphrase->จำนวนมาก</li>
		<li>trans->จาก</li>
		<li>trans->สำหรับ</li>
		<li>trans->ของ</li>
		<li>trans->กับ</li>
	</GlobalUtility.rulePack.rulesStrings>

</LanguageData>
