<?xml version="1.0" encoding="UTF-8"?>
<LanguageData>
  
  <!-- EN: ancient concrete barrier -->
  <AncientConcreteBarrier.label>คอนกรีตกั้นทางโบราณ</AncientConcreteBarrier.label>
  <!-- EN: A traffic management solution from long ago. -->
  <AncientConcreteBarrier.description>วิธีแก้ปัญหาจราจรจากเมื่อนานมาแล้ว</AncientConcreteBarrier.description>
  
  <!-- EN: ancient lamppost -->
  <AncientLamppost.label>โคมไฟถนนโบราณ</AncientLamppost.label>
  <!-- EN: Road lighting from long ago. No longer functional. -->
  <AncientLamppost.description>ไฟให้แสงกับถนนจากเมื่อนานมาแล้ว ใช้งานไม่ได้อีกต่อไป</AncientLamppost.description>
  
  <!-- EN: urn -->
  <Urn.label>TODO</Urn.label>
  <!-- EN: An ancient-style decorative container. -->
  <Urn.description>TODO</Urn.description>
  
</LanguageData>