<?xml version="1.0" encoding="UTF-8"?>
<LanguageData>
  
  <!-- EN: Armor - Blunt -->
  <StuffPower_Armor_Blunt.label>เกราะ - กันกระแทก</StuffPower_Armor_Blunt.label>
  <!-- EN: Armor against blunt damage like club impacts, rock falls, and explosions. -->
  <StuffPower_Armor_Blunt.description>เกราะป้องกันความเสียหายจากแรงกระแทก เช่น โดนตระบองตี ก้อนหินกระแทก และแรงระเบิด</StuffPower_Armor_Blunt.description>
  <!-- EN: Armor - Blunt (material factor) -->
  <StuffPower_Armor_Blunt.labelForFullStatList>กันกระแทก (ปัจจัยด้านวัสดุ)</StuffPower_Armor_Blunt.labelForFullStatList>
  
  <!-- EN: Armor - Heat -->
  <StuffPower_Armor_Heat.label>เกราะ - กันร้อน</StuffPower_Armor_Heat.label>
  <!-- EN: Armor against temperature-related damage like burns. -->
  <StuffPower_Armor_Heat.description>เกราะป้องกันความเสียหายที่เกี่ยวกับอุณภูมิ เช่น ไฟไหม้</StuffPower_Armor_Heat.description>
  <!-- EN: Armor - Heat (material factor) -->
  <StuffPower_Armor_Heat.labelForFullStatList>กันร้อน (ปัจจัยด้านวัสดุ)</StuffPower_Armor_Heat.labelForFullStatList>
  
  <!-- EN: Armor - Sharp -->
  <StuffPower_Armor_Sharp.label>เกราะ - กันคม</StuffPower_Armor_Sharp.label>
  <!-- EN: Armor against sharp damage like bullets, knife stabs, and animal bites. -->
  <StuffPower_Armor_Sharp.description>เกราะป้องกันความเสียหายจากวัตถุมีคม เช่น กระสุน โดนมีดแทง และสัตว์กัด</StuffPower_Armor_Sharp.description>
  <!-- EN: Armor - Sharp (material factor) -->
  <StuffPower_Armor_Sharp.labelForFullStatList>กันคม (ปัจจัยด้านวัสดุ)</StuffPower_Armor_Sharp.labelForFullStatList>
  
  <!-- EN: Insulation - Cold -->
  <StuffPower_Insulation_Cold.label>ฉนวนกัน - ความเย็น</StuffPower_Insulation_Cold.label>
  <!-- EN: How much an apparel made of this material improves a wearer's minimum comfortable temperature when worn. -->
  <StuffPower_Insulation_Cold.description>เสื้อผ้าที่ทำด้วยวัตถุดิบนี้ จะช่วยเพิ่ม 'อุณหภูมิต่ำสุดที่สบายตัว' ของผู้ใส่ให้ดีขึ้นแค่ไหน</StuffPower_Insulation_Cold.description>
  <!-- EN: Insulation - Cold (material factor) -->
  <StuffPower_Insulation_Cold.labelForFullStatList>ความเย็น (ปัจจัยด้านวัสดุ)</StuffPower_Insulation_Cold.labelForFullStatList>
  
  <!-- EN: Insulation - Heat -->
  <StuffPower_Insulation_Heat.label>ฉนวนกัน - ความร้อน</StuffPower_Insulation_Heat.label>
  <!-- EN: How much an apparel made of this material improves a wearer's maximum comfortable temperature when worn. -->
  <StuffPower_Insulation_Heat.description>เสื้อผ้าที่ทำด้วยวัตถุดิบนี้ จะช่วยเพิ่ม 'อุณหภูมิสูงสุดที่สบายตัว' ของผู้ใส่ให้ดีขึ้นแค่ไหน</StuffPower_Insulation_Heat.description>
  <!-- EN: Insulation - Heat (material factor) -->
  <StuffPower_Insulation_Heat.labelForFullStatList>ความร้อน (ปัจจัยด้านวัสดุ)</StuffPower_Insulation_Heat.labelForFullStatList>
  
</LanguageData>