<?xml version="1.0" encoding="UTF-8"?>
<LanguageData>

  <Afro.label>อัฟโร่</Afro.label>
  <Bob.label>บ๊อบ</Bob.label>
  <Burgundy.label>เบอร์กันดี้</Burgundy.label>
  <Flowy.label>หยิก</Flowy.label>
  <Long.label>ผมยาว</Long.label>
  <Mohawk.label>โมฮอร์ค</Mohawk.label>
  <Mop.label>ม็อป</Mop.label>
  <Pigtails.label>ผมเปีย</Pigtails.label>
  <Shaved.label>โกน</Shaved.label>
  <Spikes.label>หนาม</Spikes.label>
  <Tuft.label>Gestrubbelt</Tuft.label>
  <Wavy.label>เป็นลอน</Wavy.label>
  <BraidedKnot.label>ถักปม</BraidedKnot.label>
  <Topdog.label>Topdog</Topdog.label>
  <Senorita.label>Senorita</Senorita.label>
  <ScorpionTail.label>Skorpion-Schwanz</ScorpionTail.label>
  <BriefPonytail.label>Kurzer Pferdeschwanz</BriefPonytail.label>
  <Troubadour.label>Minnesänger</Troubadour.label>
  <Messy.label>ยุ่ง</Messy.label>
  <Princess.label>เจ้าหญิง</Princess.label>
  <Firestarter.label>Feuerteufel</Firestarter.label>
  <GreasySwoop.label>Schmalzlocke</GreasySwoop.label>
  <Curly.label>Lockig</Curly.label>
  <Scatman.label>Scatman</Scatman.label>

</LanguageData>
